dspreview-0.1.9.dist-info/METADATA
dspreview-0.1.9.dist-info/RECORD
dspreview-0.1.9.dist-info/WHEEL
dspreview-0.1.9.dist-info/entry_points.txt
dspreview-0.1.9.dist-info/top_level.txt
utils/__init__.py
utils/bucket_helper.py
utils/config_helper.py
utils/sql_helper.py
webapp/__init__.py
webapp/config.py
webapp/run.py
webapp/app/__init__.py
webapp/app/models.py
webapp/app/queries.py
webapp/app/admin/__init__.py
webapp/app/admin/forms.py
webapp/app/admin/views.py
webapp/app/auth/__init__.py
webapp/app/auth/forms.py
webapp/app/auth/views.py
webapp/app/home/__init__.py
webapp/app/home/forms.py
webapp/app/home/views.py
webapp/app/static/css/style.css
webapp/app/static/img/favicon.ico
webapp/app/static/img/intro-bg.jpg
webapp/app/static/js/jquery.js
webapp/app/templates/base.html
webapp/app/templates/auth/login.html
webapp/app/templates/auth/register.html
webapp/app/templates/errors/403.html
webapp/app/templates/errors/404.html
webapp/app/templates/errors/500.html
webapp/app/templates/home/classification.html
webapp/app/templates/home/classifications.html
webapp/app/templates/home/dashboard.html
webapp/app/templates/home/index.html
workers/__init__.py
workers/cli.py
workers/worker.py
