Metadata-Version: 2.1
Name: dspreview
Version: 0.1.9
Summary: a simple preview for dsp digital advertising information
Home-page: https://github.com/thiagolcmelo/dspreview
Author: Thiago Melo
Author-email: thiago.lc.melo@gmail.com
License: UNKNOWN
Download-URL: https://github.com/thiagolcmelo/dspreview/archive/v0.1.9.tar.gz
Platform: UNKNOWN
Classifier: Programming Language :: Python :: 3
Classifier: License :: OSI Approved :: MIT License
Classifier: Operating System :: OS Independent
Requires-Dist: alembic (==1.0.0)
Requires-Dist: cachetools (==2.1.0)
Requires-Dist: certifi (==2018.8.24)
Requires-Dist: chardet (==3.0.4)
Requires-Dist: click (==6.7)
Requires-Dist: dominate (==2.3.1)
Requires-Dist: flask-bootstrap (==3.3.7.1)
Requires-Dist: flask-login (==0.4.1)
Requires-Dist: flask-migrate (==2.2.1)
Requires-Dist: flask-sqlalchemy (==2.3.2)
Requires-Dist: flask-testing (==0.7.1)
Requires-Dist: flask-wtf (==0.14.2)
Requires-Dist: flask (==1.0.2)
Requires-Dist: google-api-python-client (==1.6.6)
Requires-Dist: google-auth-httplib2 (==0.0.3)
Requires-Dist: google-auth (==1.4.1)
Requires-Dist: httplib2 (==0.11.3)
Requires-Dist: idna (==2.7)
Requires-Dist: itsdangerous (==0.24)
Requires-Dist: jinja2 (==2.10)
Requires-Dist: mako (==1.0.7)
Requires-Dist: markupsafe (==1.0)
Requires-Dist: mysqlclient (==1.3.13)
Requires-Dist: oauth2client (==4.1.2)
Requires-Dist: pandas (==0.23.4)
Requires-Dist: pika (==0.12.0)
Requires-Dist: pkginfo (==1.4.2)
Requires-Dist: psycopg2 (==2.7.5)
Requires-Dist: pyasn1-modules (==0.2.2)
Requires-Dist: pyasn1 (==0.4.4)
Requires-Dist: python-dateutil (==2.7.3)
Requires-Dist: python-editor (==1.0.3)
Requires-Dist: pytz (==2018.5)
Requires-Dist: requests (==2.19.1)
Requires-Dist: rsa (==3.4.2)
Requires-Dist: six (==1.11.0)
Requires-Dist: sqlalchemy (==1.2.11)
Requires-Dist: twine (==1.11.0)
Requires-Dist: uritemplate (==3.0.0)
Requires-Dist: visitor (==0.1.3)
Requires-Dist: werkzeug (==0.14.1)
Requires-Dist: wtforms (==2.2.1)
Requires-Dist: urllib3 (==1.23); python_version != "3.2.*"
Requires-Dist: numpy (==1.15.1); python_version != "3.3.*"
Requires-Dist: requests-toolbelt (==0.8.0); python_version < "4"
Requires-Dist: tqdm (==4.25.0); python_version >= "2.6"
